EPICstuff/ADCPcdf2ncEPIC.py
EPICstuff/EPICmisc.py
EPICstuff/__init__.py
EPICstuff/doreshape.py
EPICstuff/doreshapemultifile.py
EPICstuff/repopulateEPIC.py
EPICstuff/reshapeEPIC.py
Nortekstuff/Norteknc2USGScdf.py
Nortekstuff/__init__.py
TRDIstuff/TRDIpd0tonetcdf.py
TRDIstuff/__init__.py
TRDIstuff/pd0.py
TRDIstuff/pd0splitter.py
adcpy/__init__.py
adcpy/EPICstuff/ADCPcdf2ncEPIC.py
adcpy/EPICstuff/EPICmisc.py
adcpy/EPICstuff/__init__.py
adcpy/EPICstuff/doreshape.py
adcpy/EPICstuff/doreshapemultifile.py
adcpy/EPICstuff/repopulateEPIC.py
adcpy/EPICstuff/reshapeEPIC.py
adcpy/Nortekstuff/Norteknc2USGScdf.py
adcpy/Nortekstuff/__init__.py
adcpy/TRDIstuff/TRDIpd0tonetcdf.py
adcpy/TRDIstuff/__init__.py
adcpy/TRDIstuff/pd0.py
adcpy/TRDIstuff/pd0splitter.py
ADCPy-0.1.1.dist-info/LICENSE.md
ADCPy-0.1.1.dist-info/METADATA
ADCPy-0.1.1.dist-info/WHEEL
ADCPy-0.1.1.dist-info/top_level.txt
ADCPy-0.1.1.dist-info/RECORD
