Metadata-Version: 2.1
Name: ADCPy
Version: 0.1.1
Summary: read ADCP data from TRDI and Nortek instruments
Home-page: https://github.com/mmartini-usgs/ADCPy
Author: Marinna Martini
Author-email: mmartini@usgs.gov
License: UNKNOWN
Keywords: acoustic doppler profiler ADCP
Platform: UNKNOWN
Classifier: Programming Language :: Python :: 3
Classifier: License :: Public Domain
Classifier: Operating System :: OS Independent
Classifier: Development Status :: 3 - Alpha
Classifier: Intended Audience :: Science/Research
Requires-Python: >=3.5
